bigquery_views_manager/__init__.py
bigquery_views_manager/__main__.py
bigquery_views_manager/cli.py
bigquery_views_manager/config_tables.py
bigquery_views_manager/configure_warnings.py
bigquery_views_manager/delete_views_or_tables.py
bigquery_views_manager/diff_views.py
bigquery_views_manager/get_views.py
bigquery_views_manager/materialize_views.py
bigquery_views_manager/materialize_views_typing.py
bigquery_views_manager/update_views.py
bigquery_views_manager/view_dependencies.py
bigquery_views_manager/view_list.py
bigquery_views_manager/view_template.py
bigquery_views_manager/views.py
bigquery_views_manager/utils/__init__.py
bigquery_views_manager/utils/bigquery.py
bigquery_views_manager/utils/json.py
tests/__init__.py
tests/cli_test.py
tests/config_tables_test.py
tests/conftest.py
tests/delete_views_or_tables_test.py
tests/diff_views_test.py
tests/materialize_views_test.py
tests/update_views_test.py
tests/view_dependencies_test.py
tests/view_list_test.py
tests/view_template_test.py
tests/views_test.py
tests/utils/__init__.py
tests/utils/bigquery_test.py
tests/utils/json_test.py
bigquery_views_manager-1.0.18.dist-info/METADATA
bigquery_views_manager-1.0.18.dist-info/WHEEL
bigquery_views_manager-1.0.18.dist-info/top_level.txt
bigquery_views_manager-1.0.18.dist-info/RECORD
