Metadata-Version: 2.1
Name: bigquery-views-manager
Version: 1.0.18
Summary: BigQuery Views Manager
Home-page: https://github.com/elifesciences/bigquery-views-manager
Author: eLife Sciences Publications, Ltd
Classifier: Programming Language :: Python :: 3
Classifier: License :: OSI Approved :: MIT License
Classifier: Operating System :: OS Independent
Requires-Dist: google-cloud-bigquery
Requires-Dist: crayons
Requires-Dist: PyYAML
